yabci/__init__.py
yabci/importer.py
yabci/logger.py
yabci/utils.py
yabci-0.3.2.dist-info/LICENSE
yabci-0.3.2.dist-info/METADATA
yabci-0.3.2.dist-info/WHEEL
yabci-0.3.2.dist-info/top_level.txt
yabci-0.3.2.dist-info/RECORD
