Metadata-Version: 2.1
Name: yabci
Version: 0.3.2
Summary: Yet another beancount importer - import any file formats, with total customization
Author: privatize-koala
License: GNU AFFERO GENERAL PUBLIC LICENSE
Project-URL: Homepage, https://codeberg.org/privatize-koala/yabci
Project-URL: Bug Tracker, https://codeberg.org/privatize-koala/yabci/issues
Keywords: beancount,importer
Classifier: Programming Language :: Python :: 3
Classifier: Development Status :: 4 - Beta
Classifier: License :: OSI Approved :: GNU Affero General Public License v3 or later (AGPLv3+)
Classifier: Operating System :: OS Independent
Classifier: Topic :: Office/Business :: Financial :: Accounting
Requires-Python: >=3.7
License-File: LICENSE
Requires-Dist: python-benedict
Requires-Dist: beancount
Requires-Dist: python-dateutil
